{
    "name": "Daredevil Blueprint",
    "volume": 0.01,
    "products": "Daredevil",
    "tech level": 6,
    "manufacturing time": "10:00:00",
    "manufacturing cost": 55000000,
    "pi requirements": {
        "condensed alloy": 45090,
        "precious alloy": 35333,
        "fiber composite": 45090,
        "reactive metals": 11213,
        "toxic metals": 11120
    },
    "ore requirements": {
        "tritanium": 20277863,
        "pyrite": 5866340,
        "mexallon": 1996632,
        "isogen": 286763,
        "noxium": 77985
    }
}