{
    "name": "Capital Computer System Blueprint",
    "volume": 0.01,
    "products": "Capital Computer System",
    "tech level": 9,
    "manufacturing time": "24:00:00",
    "manufacturing cost": 150000000,
    "pi requirements": {
        "lustering alloy": 85029,
        "motley compound": 85578,
        "lucent compound": 91613,
        "dark compound": 91613,
        "noble metals": 96962
    },
    "ore requirements": {
        "tritanium": 7543845,
        "pyrite": 1828866,
        "mexallon": 547883,
        "isogen": 87744,
        "noxium": 26856,
        "zydrine": 10128,
        "megacyte": 4841,
        "morphite": 1772
    }
}