{
    "name": "MK9 Ogre Blueprint",
    "volume": 0.01,
    "products": "MK9 Ogre",
    "tech level": 9,
    "manufacturing time": "01:00:00",
    "manufacturing cost": 8000000,
    "pi requirements": {
        "lustering alloy": 10989,
        "motley compound": 10410,
        "crystal compound": 11807,
        "base metals": 4340,
        "reactive metals": 3383
    },
    "ore requirements": {
        "tritanium": 430485,
        "pyrite": 135093,
        "mexallon": 33900,
        "isogen": 7818,
        "noxium": 1721,
        "zydrine": 669,
        "megacyte": 386
    }
}