{
    "name": "Integrated Satyr Blueprint",
    "volume": 0.01,
    "products": "Integrated Satyr",
    "tech level": 10,
    "manufacturing time": "06:00:00",
    "manufacturing cost": 20000000,
    "pi requirements": {
        "sheen compound": 135456,
        "fiber composite": 113399,
        "crystal compound": 110115,
        "heavy mentals": 98816,
        "toxic metals": 26805,
        "precious metals": 13527,
        "non-cs crystals": 14718
    },
    "ore requirements": {
        "tritanium": 4802051,
        "pyrite": 909984,
        "mexallon": 345909,
        "isogen": 60546,
        "noxium": 16361,
        "zydrine": 6470,
        "megacyte": 2888,
        "morphite": 1008
    }
}